{
  "archetype": "Azir, Emperor",
  "url": "https://riftdecks.com/riftbound-decks?omni=azir%2C+emperor",
  "scraped_at": "2026-05-10T17:43:07.044105Z",
  "deck_count": 1292,
  "cards": [
    {
      "slug": "details-azir-emperor-of-the-sands",
      "name": "Azir, Emperor of the Sands",
      "type": "legend",
      "domains": [
        "calm",
        "order"
      ],
      "cost": "-",
      "rarity": "rare",
      "url": "https://riftdecks.com/cards/details-azir-emperor-of-the-sands",
      "decks_including": 1292,
      "inclusion_pct": 100.0,
      "avg_copies_when_included": 1.0,
      "copies_pct": {
        "0": 0.0,
        "1": 100.0,
        "2": 0.0,
        "3+": 0.0
      }
    },
    {
      "slug": "details-calm-rune",
      "name": "Calm Rune",
      "type": "rune",
      "domains": [
        "calm"
      ],
      "cost": "-",
      "rarity": "common",
      "url": "https://riftdecks.com/cards/details-calm-rune",
      "decks_including": 1292,
      "inclusion_pct": 100.0,
      "avg_copies_when_included": 5.72,
      "copies_pct": {
        "0": 0.0,
        "1": 0.0,
        "2": 0.0,
        "3+": 100.0
      }
    },
    {
      "slug": "details-order-rune",
      "name": "Order Rune",
      "type": "rune",
      "domains": [
        "order"
      ],
      "cost": "-",
      "rarity": "showcase",
      "url": "https://riftdecks.com/cards/details-order-rune",
      "decks_including": 1292,
      "inclusion_pct": 100.0,
      "avg_copies_when_included": 6.28,
      "copies_pct": {
        "0": 0.0,
        "1": 0.0,
        "2": 0.0,
        "3+": 100.0
      }
    },
    {
      "slug": "details-dorans-shield",
      "name": "Doran's Shield",
      "type": "gear",
      "domains": [
        "calm"
      ],
      "cost": "1",
      "rarity": "common",
      "url": "https://riftdecks.com/cards/details-dorans-shield",
      "decks_including": 1281,
      "inclusion_pct": 99.1,
      "avg_copies_when_included": 2.97,
      "copies_pct": {
        "0": 0.9,
        "1": 0.0,
        "2": 2.6,
        "3+": 96.5
      }
    },
    {
      "slug": "details-brutalizer",
      "name": "Brutalizer",
      "type": "gear",
      "domains": [
        "calm"
      ],
      "cost": "2",
      "rarity": "uncommon",
      "url": "https://riftdecks.com/cards/details-brutalizer",
      "decks_including": 1280,
      "inclusion_pct": 99.1,
      "avg_copies_when_included": 2.74,
      "copies_pct": {
        "0": 0.9,
        "1": 2.2,
        "2": 21.1,
        "3+": 75.8
      }
    },
    {
      "slug": "details-eye-of-the-herald",
      "name": "Eye of the Herald",
      "type": "gear",
      "domains": [
        "order"
      ],
      "cost": "1",
      "rarity": "common",
      "url": "https://riftdecks.com/cards/details-eye-of-the-herald",
      "decks_including": 1273,
      "inclusion_pct": 98.5,
      "avg_copies_when_included": 2.96,
      "copies_pct": {
        "0": 1.5,
        "1": 0.6,
        "2": 2.9,
        "3+": 95.0
      }
    },
    {
      "slug": "details-arise",
      "name": "Arise!",
      "type": "spell",
      "domains": [
        "calm",
        "order"
      ],
      "cost": "6C",
      "rarity": "epic",
      "url": "https://riftdecks.com/cards/details-arise",
      "decks_including": 1261,
      "inclusion_pct": 97.6,
      "avg_copies_when_included": 2.6,
      "copies_pct": {
        "0": 2.4,
        "1": 5.7,
        "2": 27.5,
        "3+": 64.4
      }
    },
    {
      "slug": "details-hidden-blade",
      "name": "Hidden Blade",
      "type": "spell",
      "domains": [
        "order"
      ],
      "cost": "2C",
      "rarity": "common",
      "url": "https://riftdecks.com/cards/details-hidden-blade",
      "decks_including": 1212,
      "inclusion_pct": 93.8,
      "avg_copies_when_included": 2.46,
      "copies_pct": {
        "0": 6.2,
        "1": 4.5,
        "2": 41.9,
        "3+": 47.4
      }
    },
    {
      "slug": "details-azir-sovereign",
      "name": "Azir, Sovereign",
      "type": "unit",
      "domains": [
        "order"
      ],
      "cost": "4",
      "rarity": "showcase",
      "url": "https://riftdecks.com/cards/details-azir-sovereign",
      "decks_including": 1186,
      "inclusion_pct": 91.8,
      "avg_copies_when_included": 1.12,
      "copies_pct": {
        "0": 8.2,
        "1": 82.4,
        "2": 7.5,
        "3+": 1.9
      }
    },
    {
      "slug": "details-b-f-sword",
      "name": "B.F. Sword",
      "type": "gear",
      "domains": [
        "order"
      ],
      "cost": "4",
      "rarity": "uncommon",
      "url": "https://riftdecks.com/cards/details-b-f-sword",
      "decks_including": 1186,
      "inclusion_pct": 91.8,
      "avg_copies_when_included": 2.65,
      "copies_pct": {
        "0": 8.2,
        "1": 6.2,
        "2": 19.4,
        "3+": 66.2
      }
    },
    {
      "slug": "details-defy",
      "name": "Defy",
      "type": "spell",
      "domains": [
        "calm"
      ],
      "cost": "1C",
      "rarity": "common",
      "url": "https://riftdecks.com/cards/details-defy",
      "decks_including": 1154,
      "inclusion_pct": 89.3,
      "avg_copies_when_included": 2.32,
      "copies_pct": {
        "0": 10.7,
        "1": 7.4,
        "2": 46.0,
        "3+": 35.9
      }
    },
    {
      "slug": "details-deserts-call",
      "name": "Desert's Call",
      "type": "spell",
      "domains": [
        "calm"
      ],
      "cost": "2",
      "rarity": "common",
      "url": "https://riftdecks.com/cards/details-deserts-call",
      "decks_including": 1129,
      "inclusion_pct": 87.4,
      "avg_copies_when_included": 2.59,
      "copies_pct": {
        "0": 12.6,
        "1": 4.1,
        "2": 27.3,
        "3+": 56.0
      }
    },
    {
      "slug": "details-ornns-forge",
      "name": "Ornn's Forge",
      "type": "battlefield",
      "domains": [
        "colorless"
      ],
      "cost": "-",
      "rarity": "uncommon",
      "url": "https://riftdecks.com/cards/details-ornns-forge",
      "decks_including": 1049,
      "inclusion_pct": 81.2,
      "avg_copies_when_included": 1.0,
      "copies_pct": {
        "0": 18.8,
        "1": 81.2,
        "2": 0.0,
        "3+": 0.0
      }
    },
    {
      "slug": "details-cull-the-weak",
      "name": "Cull the Weak",
      "type": "spell",
      "domains": [
        "order"
      ],
      "cost": "2C",
      "rarity": "common",
      "url": "https://riftdecks.com/cards/details-cull-the-weak",
      "decks_including": 1025,
      "inclusion_pct": 79.3,
      "avg_copies_when_included": 2.3,
      "copies_pct": {
        "0": 20.7,
        "1": 9.4,
        "2": 36.9,
        "3+": 33.0
      }
    },
    {
      "slug": "details-guards",
      "name": "Guards!",
      "type": "spell",
      "domains": [
        "order"
      ],
      "cost": "3",
      "rarity": "common",
      "url": "https://riftdecks.com/cards/details-guards",
      "decks_including": 878,
      "inclusion_pct": 68.0,
      "avg_copies_when_included": 2.19,
      "copies_pct": {
        "0": 32.0,
        "1": 8.4,
        "2": 38.3,
        "3+": 21.3
      }
    },
    {
      "slug": "details-discipline",
      "name": "Discipline",
      "type": "spell",
      "domains": [
        "calm"
      ],
      "cost": "2",
      "rarity": "uncommon",
      "url": "https://riftdecks.com/cards/details-discipline",
      "decks_including": 873,
      "inclusion_pct": 67.6,
      "avg_copies_when_included": 2.64,
      "copies_pct": {
        "0": 32.4,
        "1": 1.5,
        "2": 21.7,
        "3+": 44.4
      }
    },
    {
      "slug": "details-deathgrip",
      "name": "Deathgrip",
      "type": "spell",
      "domains": [
        "order"
      ],
      "cost": "2",
      "rarity": "uncommon",
      "url": "https://riftdecks.com/cards/details-deathgrip",
      "decks_including": 864,
      "inclusion_pct": 66.9,
      "avg_copies_when_included": 2.17,
      "copies_pct": {
        "0": 33.1,
        "1": 13.1,
        "2": 29.6,
        "3+": 24.2
      }
    },
    {
      "slug": "details-trifarian-war-camp",
      "name": "Trifarian War Camp",
      "type": "battlefield",
      "domains": [
        "colorless"
      ],
      "cost": "-",
      "rarity": "uncommon",
      "url": "https://riftdecks.com/cards/details-trifarian-war-camp",
      "decks_including": 826,
      "inclusion_pct": 63.9,
      "avg_copies_when_included": 1.0,
      "copies_pct": {
        "0": 36.1,
        "1": 63.9,
        "2": 0.0,
        "3+": 0.0
      }
    },
    {
      "slug": "details-sacred-shears",
      "name": "Sacred Shears",
      "type": "gear",
      "domains": [
        "order"
      ],
      "cost": "2C",
      "rarity": "rare",
      "url": "https://riftdecks.com/cards/details-sacred-shears",
      "decks_including": 823,
      "inclusion_pct": 63.7,
      "avg_copies_when_included": 2.16,
      "copies_pct": {
        "0": 36.3,
        "1": 9.1,
        "2": 35.0,
        "3+": 19.6
      }
    },
    {
      "slug": "details-guardian-angel",
      "name": "Guardian Angel",
      "type": "gear",
      "domains": [
        "calm"
      ],
      "cost": "2",
      "rarity": "rare",
      "url": "https://riftdecks.com/cards/details-guardian-angel",
      "decks_including": 801,
      "inclusion_pct": 62.0,
      "avg_copies_when_included": 2.27,
      "copies_pct": {
        "0": 38.0,
        "1": 10.6,
        "2": 24.0,
        "3+": 27.4
      }
    },
    {
      "slug": "details-hall-of-legends",
      "name": "Hall of Legends",
      "type": "battlefield",
      "domains": [
        "colorless"
      ],
      "cost": "-",
      "rarity": "uncommon",
      "url": "https://riftdecks.com/cards/details-hall-of-legends",
      "decks_including": 781,
      "inclusion_pct": 60.4,
      "avg_copies_when_included": 1.0,
      "copies_pct": {
        "0": 39.6,
        "1": 60.4,
        "2": 0.0,
        "3+": 0.0
      }
    },
    {
      "slug": "details-grand-strategem",
      "name": "Grand Strategem",
      "type": "spell",
      "domains": [
        "order"
      ],
      "cost": "6CCC",
      "rarity": "rare",
      "url": "https://riftdecks.com/cards/details-grand-strategem",
      "decks_including": 513,
      "inclusion_pct": 39.7,
      "avg_copies_when_included": 1.71,
      "copies_pct": {
        "0": 60.3,
        "1": 12.1,
        "2": 27.2,
        "3+": 0.4
      }
    },
    {
      "slug": "details-emperors-divide",
      "name": "Emperor's Divide",
      "type": "spell",
      "domains": [
        "calm"
      ],
      "cost": "2",
      "rarity": "uncommon",
      "url": "https://riftdecks.com/cards/details-emperors-divide",
      "decks_including": 489,
      "inclusion_pct": 37.8,
      "avg_copies_when_included": 1.46,
      "copies_pct": {
        "0": 62.2,
        "1": 22.7,
        "2": 13.0,
        "3+": 2.2
      }
    },
    {
      "slug": "details-not-so-fast",
      "name": "Not So Fast",
      "type": "spell",
      "domains": [
        "calm"
      ],
      "cost": "2C",
      "rarity": "uncommon",
      "url": "https://riftdecks.com/cards/details-not-so-fast",
      "decks_including": 478,
      "inclusion_pct": 37.0,
      "avg_copies_when_included": 1.49,
      "copies_pct": {
        "0": 63.0,
        "1": 19.0,
        "2": 18.0,
        "3+": 0.0
      }
    },
    {
      "slug": "details-wind-wall",
      "name": "Wind Wall",
      "type": "spell",
      "domains": [
        "calm"
      ],
      "cost": "3CC",
      "rarity": "uncommon",
      "url": "https://riftdecks.com/cards/details-wind-wall",
      "decks_including": 406,
      "inclusion_pct": 31.4,
      "avg_copies_when_included": 1.31,
      "copies_pct": {
        "0": 68.6,
        "1": 22.8,
        "2": 7.7,
        "3+": 0.9
      }
    },
    {
      "slug": "details-renata-glasc-industrialist",
      "name": "Renata Glasc, Industrialist",
      "type": "unit",
      "domains": [
        "order"
      ],
      "cost": "4C",
      "rarity": "showcase",
      "url": "https://riftdecks.com/cards/details-renata-glasc-industrialist",
      "decks_including": 376,
      "inclusion_pct": 29.1,
      "avg_copies_when_included": 1.72,
      "copies_pct": {
        "0": 70.9,
        "1": 12.4,
        "2": 12.4,
        "3+": 4.3
      }
    },
    {
      "slug": "details-thwonk",
      "name": "Thwonk!",
      "type": "spell",
      "domains": [
        "calm"
      ],
      "cost": "2",
      "rarity": "common",
      "url": "https://riftdecks.com/cards/details-thwonk",
      "decks_including": 360,
      "inclusion_pct": 27.9,
      "avg_copies_when_included": 1.69,
      "copies_pct": {
        "0": 72.1,
        "1": 9.5,
        "2": 17.5,
        "3+": 0.9
      }
    },
    {
      "slug": "details-azir-ascendant",
      "name": "Azir, Ascendant",
      "type": "unit",
      "domains": [
        "calm"
      ],
      "cost": "6C",
      "rarity": "rare",
      "url": "https://riftdecks.com/cards/details-azir-ascendant",
      "decks_including": 337,
      "inclusion_pct": 26.1,
      "avg_copies_when_included": 1.27,
      "copies_pct": {
        "0": 73.9,
        "1": 20.0,
        "2": 5.2,
        "3+": 0.9
      }
    },
    {
      "slug": "details-salvage",
      "name": "Salvage",
      "type": "spell",
      "domains": [
        "order"
      ],
      "cost": "2C",
      "rarity": "uncommon",
      "url": "https://riftdecks.com/cards/details-salvage",
      "decks_including": 326,
      "inclusion_pct": 25.2,
      "avg_copies_when_included": 1.3,
      "copies_pct": {
        "0": 74.8,
        "1": 18.5,
        "2": 5.8,
        "3+": 0.9
      }
    },
    {
      "slug": "details-imperial-decree",
      "name": "Imperial Decree",
      "type": "spell",
      "domains": [
        "order"
      ],
      "cost": "5CC",
      "rarity": "uncommon",
      "url": "https://riftdecks.com/cards/details-imperial-decree",
      "decks_including": 265,
      "inclusion_pct": 20.5,
      "avg_copies_when_included": 1.6,
      "copies_pct": {
        "0": 79.5,
        "1": 10.3,
        "2": 8.0,
        "3+": 2.2
      }
    },
    {
      "slug": "details-charm",
      "name": "Charm",
      "type": "spell",
      "domains": [
        "calm"
      ],
      "cost": "1C",
      "rarity": "common",
      "url": "https://riftdecks.com/cards/details-charm",
      "decks_including": 247,
      "inclusion_pct": 19.1,
      "avg_copies_when_included": 1.32,
      "copies_pct": {
        "0": 80.9,
        "1": 14.1,
        "2": 4.0,
        "3+": 1.0
      }
    },
    {
      "slug": "details-honest-broker",
      "name": "Honest Broker",
      "type": "unit",
      "domains": [
        "order"
      ],
      "cost": "2",
      "rarity": "common",
      "url": "https://riftdecks.com/cards/details-honest-broker",
      "decks_including": 246,
      "inclusion_pct": 19.0,
      "avg_copies_when_included": 2.1,
      "copies_pct": {
        "0": 81.0,
        "1": 3.9,
        "2": 9.4,
        "3+": 5.7
      }
    },
    {
      "slug": "details-blade-of-the-ruined-king",
      "name": "Blade of the Ruined King",
      "type": "gear",
      "domains": [
        "order"
      ],
      "cost": "3C",
      "rarity": "epic",
      "url": "https://riftdecks.com/cards/details-blade-of-the-ruined-king",
      "decks_including": 212,
      "inclusion_pct": 16.4,
      "avg_copies_when_included": 1.53,
      "copies_pct": {
        "0": 83.6,
        "1": 10.3,
        "2": 3.5,
        "3+": 2.6
      }
    },
    {
      "slug": "details-tasty-faefolk",
      "name": "Tasty Faefolk",
      "type": "unit",
      "domains": [
        "calm"
      ],
      "cost": "7",
      "rarity": "rare",
      "url": "https://riftdecks.com/cards/details-tasty-faefolk",
      "decks_including": 173,
      "inclusion_pct": 13.4,
      "avg_copies_when_included": 1.62,
      "copies_pct": {
        "0": 86.6,
        "1": 5.0,
        "2": 8.4,
        "3+": 0.0
      }
    },
    {
      "slug": "details-treasure-hoard",
      "name": "Treasure Hoard",
      "type": "battlefield",
      "domains": [
        "colorless"
      ],
      "cost": "-",
      "rarity": "uncommon",
      "url": "https://riftdecks.com/cards/details-treasure-hoard",
      "decks_including": 157,
      "inclusion_pct": 12.2,
      "avg_copies_when_included": 1.0,
      "copies_pct": {
        "0": 87.8,
        "1": 12.2,
        "2": 0.0,
        "3+": 0.0
      }
    },
    {
      "slug": "details-janna-savior",
      "name": "Janna, Savior",
      "type": "unit",
      "domains": [
        "calm"
      ],
      "cost": "3C",
      "rarity": "rare",
      "url": "https://riftdecks.com/cards/details-janna-savior",
      "decks_including": 148,
      "inclusion_pct": 11.5,
      "avg_copies_when_included": 1.47,
      "copies_pct": {
        "0": 88.5,
        "1": 6.1,
        "2": 5.3,
        "3+": 0.0
      }
    },
    {
      "slug": "details-shadows-call",
      "name": "Shadow's Call",
      "type": "spell",
      "domains": [
        "order"
      ],
      "cost": "2",
      "rarity": "uncommon",
      "url": "https://riftdecks.com/cards/details-shadows-call",
      "decks_including": 141,
      "inclusion_pct": 10.9,
      "avg_copies_when_included": 2.12,
      "copies_pct": {
        "0": 89.1,
        "1": 0.9,
        "2": 7.7,
        "3+": 2.2
      }
    },
    {
      "slug": "details-soul-sword",
      "name": "Soul Sword",
      "type": "gear",
      "domains": [
        "calm"
      ],
      "cost": "1",
      "rarity": "common",
      "url": "https://riftdecks.com/cards/details-soul-sword",
      "decks_including": 135,
      "inclusion_pct": 10.4,
      "avg_copies_when_included": 2.55,
      "copies_pct": {
        "0": 89.6,
        "1": 0.8,
        "2": 3.2,
        "3+": 6.5
      }
    },
    {
      "slug": "details-find-your-center",
      "name": "Find Your Center",
      "type": "spell",
      "domains": [
        "calm"
      ],
      "cost": "3",
      "rarity": "common",
      "url": "https://riftdecks.com/cards/details-find-your-center",
      "decks_including": 131,
      "inclusion_pct": 10.1,
      "avg_copies_when_included": 2.21,
      "copies_pct": {
        "0": 89.9,
        "1": 1.1,
        "2": 5.8,
        "3+": 3.3
      }
    },
    {
      "slug": "details-sacrifice",
      "name": "Sacrifice",
      "type": "spell",
      "domains": [
        "order"
      ],
      "cost": "1",
      "rarity": "rare",
      "url": "https://riftdecks.com/cards/details-sacrifice",
      "decks_including": 128,
      "inclusion_pct": 9.9,
      "avg_copies_when_included": 1.96,
      "copies_pct": {
        "0": 90.1,
        "1": 1.3,
        "2": 7.7,
        "3+": 0.9
      }
    },
    {
      "slug": "details-apprentice-smith",
      "name": "Apprentice Smith",
      "type": "unit",
      "domains": [
        "calm"
      ],
      "cost": "2",
      "rarity": "uncommon",
      "url": "https://riftdecks.com/cards/details-apprentice-smith",
      "decks_including": 128,
      "inclusion_pct": 9.9,
      "avg_copies_when_included": 2.01,
      "copies_pct": {
        "0": 90.1,
        "1": 2.9,
        "2": 3.9,
        "3+": 3.0
      }
    },
    {
      "slug": "details-vilemaws-lair",
      "name": "Vilemaw's Lair",
      "type": "battlefield",
      "domains": [
        "colorless"
      ],
      "cost": "-",
      "rarity": "uncommon",
      "url": "https://riftdecks.com/cards/details-vilemaws-lair",
      "decks_including": 127,
      "inclusion_pct": 9.8,
      "avg_copies_when_included": 1.0,
      "copies_pct": {
        "0": 90.2,
        "1": 9.8,
        "2": 0.0,
        "3+": 0.0
      }
    },
    {
      "slug": "details-royal-guard",
      "name": "Royal Guard",
      "type": "unit",
      "domains": [
        "order"
      ],
      "cost": "4",
      "rarity": "common",
      "url": "https://riftdecks.com/cards/details-royal-guard",
      "decks_including": 126,
      "inclusion_pct": 9.8,
      "avg_copies_when_included": 1.81,
      "copies_pct": {
        "0": 90.2,
        "1": 3.2,
        "2": 5.3,
        "3+": 1.3
      }
    },
    {
      "slug": "details-seal-of-unity",
      "name": "Seal of Unity",
      "type": "gear",
      "domains": [
        "order"
      ],
      "cost": "0C",
      "rarity": "epic",
      "url": "https://riftdecks.com/cards/details-seal-of-unity",
      "decks_including": 117,
      "inclusion_pct": 9.1,
      "avg_copies_when_included": 2.08,
      "copies_pct": {
        "0": 90.9,
        "1": 2.0,
        "2": 4.3,
        "3+": 2.7
      }
    },
    {
      "slug": "details-rockfall-path",
      "name": "Rockfall Path",
      "type": "battlefield",
      "domains": [
        "colorless"
      ],
      "cost": "-",
      "rarity": "uncommon",
      "url": "https://riftdecks.com/cards/details-rockfall-path",
      "decks_including": 113,
      "inclusion_pct": 8.7,
      "avg_copies_when_included": 1.0,
      "copies_pct": {
        "0": 91.3,
        "1": 8.7,
        "2": 0.0,
        "3+": 0.0
      }
    },
    {
      "slug": "details-lonely-poro",
      "name": "Lonely Poro",
      "type": "unit",
      "domains": [
        "calm"
      ],
      "cost": "2",
      "rarity": "common",
      "url": "https://riftdecks.com/cards/details-lonely-poro",
      "decks_including": 110,
      "inclusion_pct": 8.5,
      "avg_copies_when_included": 1.93,
      "copies_pct": {
        "0": 91.5,
        "1": 0.6,
        "2": 7.9,
        "3+": 0.0
      }
    },
    {
      "slug": "details-soraka-wanderer",
      "name": "Soraka, Wanderer",
      "type": "unit",
      "domains": [
        "order"
      ],
      "cost": "4C",
      "rarity": "showcase",
      "url": "https://riftdecks.com/cards/details-soraka-wanderer",
      "decks_including": 101,
      "inclusion_pct": 7.8,
      "avg_copies_when_included": 1.31,
      "copies_pct": {
        "0": 92.2,
        "1": 5.4,
        "2": 2.4,
        "3+": 0.0
      }
    },
    {
      "slug": "details-back-off",
      "name": "Back Off",
      "type": "spell",
      "domains": [
        "calm"
      ],
      "cost": "3",
      "rarity": "uncommon",
      "url": "https://riftdecks.com/cards/details-back-off",
      "decks_including": 97,
      "inclusion_pct": 7.5,
      "avg_copies_when_included": 2.0,
      "copies_pct": {
        "0": 92.5,
        "1": 2.1,
        "2": 3.3,
        "3+": 2.1
      }
    },
    {
      "slug": "details-facebreaker",
      "name": "Facebreaker",
      "type": "spell",
      "domains": [
        "order"
      ],
      "cost": "2",
      "rarity": "uncommon",
      "url": "https://riftdecks.com/cards/details-facebreaker",
      "decks_including": 95,
      "inclusion_pct": 7.4,
      "avg_copies_when_included": 1.58,
      "copies_pct": {
        "0": 92.6,
        "1": 3.1,
        "2": 4.3,
        "3+": 0.0
      }
    },
    {
      "slug": "details-xin-zhao-vigilant",
      "name": "Xin Zhao, Vigilant",
      "type": "unit",
      "domains": [
        "order"
      ],
      "cost": "3C",
      "rarity": "rare",
      "url": "https://riftdecks.com/cards/details-xin-zhao-vigilant",
      "decks_including": 94,
      "inclusion_pct": 7.3,
      "avg_copies_when_included": 1.59,
      "copies_pct": {
        "0": 92.7,
        "1": 3.7,
        "2": 2.9,
        "3+": 0.7
      }
    },
    {
      "slug": "details-meditation",
      "name": "Meditation",
      "type": "spell",
      "domains": [
        "calm"
      ],
      "cost": "2",
      "rarity": "common",
      "url": "https://riftdecks.com/cards/details-meditation",
      "decks_including": 93,
      "inclusion_pct": 7.2,
      "avg_copies_when_included": 1.75,
      "copies_pct": {
        "0": 92.8,
        "1": 2.1,
        "2": 4.8,
        "3+": 0.3
      }
    },
    {
      "slug": "details-reavers-row",
      "name": "Reaver's Row",
      "type": "battlefield",
      "domains": [
        "colorless"
      ],
      "cost": "-",
      "rarity": "uncommon",
      "url": "https://riftdecks.com/cards/details-reavers-row",
      "decks_including": 91,
      "inclusion_pct": 7.0,
      "avg_copies_when_included": 1.0,
      "copies_pct": {
        "0": 93.0,
        "1": 7.0,
        "2": 0.0,
        "3+": 0.0
      }
    },
    {
      "slug": "details-vaults-of-helia",
      "name": "Vaults of Helia",
      "type": "battlefield",
      "domains": [
        "colorless"
      ],
      "cost": "-",
      "rarity": "uncommon",
      "url": "https://riftdecks.com/cards/details-vaults-of-helia",
      "decks_including": 87,
      "inclusion_pct": 6.7,
      "avg_copies_when_included": 1.0,
      "copies_pct": {
        "0": 93.3,
        "1": 6.7,
        "2": 0.0,
        "3+": 0.0
      }
    },
    {
      "slug": "details-forge-of-the-fluft",
      "name": "Forge of the Fluft",
      "type": "battlefield",
      "domains": [
        "colorless"
      ],
      "cost": "-",
      "rarity": "uncommon",
      "url": "https://riftdecks.com/cards/details-forge-of-the-fluft",
      "decks_including": 81,
      "inclusion_pct": 6.3,
      "avg_copies_when_included": 1.0,
      "copies_pct": {
        "0": 93.7,
        "1": 6.3,
        "2": 0.0,
        "3+": 0.0
      }
    },
    {
      "slug": "details-undertitan",
      "name": "Undertitan",
      "type": "unit",
      "domains": [
        "order"
      ],
      "cost": "6C",
      "rarity": "rare",
      "url": "https://riftdecks.com/cards/details-undertitan",
      "decks_including": 80,
      "inclusion_pct": 6.2,
      "avg_copies_when_included": 1.41,
      "copies_pct": {
        "0": 93.8,
        "1": 4.5,
        "2": 0.9,
        "3+": 0.9
      }
    },
    {
      "slug": "details-obelisk-of-power",
      "name": "Obelisk of Power",
      "type": "battlefield",
      "domains": [
        "colorless"
      ],
      "cost": "-",
      "rarity": "uncommon",
      "url": "https://riftdecks.com/cards/details-obelisk-of-power",
      "decks_including": 74,
      "inclusion_pct": 5.7,
      "avg_copies_when_included": 1.0,
      "copies_pct": {
        "0": 94.3,
        "1": 5.7,
        "2": 0.0,
        "3+": 0.0
      }
    },
    {
      "slug": "details-whiteflame-protector",
      "name": "Whiteflame Protector",
      "type": "unit",
      "domains": [
        "calm"
      ],
      "cost": "8CC",
      "rarity": "epic",
      "url": "https://riftdecks.com/cards/details-whiteflame-protector",
      "decks_including": 71,
      "inclusion_pct": 5.5,
      "avg_copies_when_included": 1.86,
      "copies_pct": {
        "0": 94.5,
        "1": 1.7,
        "2": 2.9,
        "3+": 0.9
      }
    },
    {
      "slug": "details-emperors-dais",
      "name": "Emperor's Dais",
      "type": "battlefield",
      "domains": [
        "colorless"
      ],
      "cost": "-",
      "rarity": "uncommon",
      "url": "https://riftdecks.com/cards/details-emperors-dais",
      "decks_including": 70,
      "inclusion_pct": 5.4,
      "avg_copies_when_included": 1.0,
      "copies_pct": {
        "0": 94.6,
        "1": 5.4,
        "2": 0.0,
        "3+": 0.0
      }
    },
    {
      "slug": "details-unsung-hero",
      "name": "Unsung Hero",
      "type": "unit",
      "domains": [
        "order"
      ],
      "cost": "2",
      "rarity": "uncommon",
      "url": "https://riftdecks.com/cards/details-unsung-hero",
      "decks_including": 68,
      "inclusion_pct": 5.3,
      "avg_copies_when_included": 1.93,
      "copies_pct": {
        "0": 94.7,
        "1": 0.8,
        "2": 4.1,
        "3+": 0.4
      }
    },
    {
      "slug": "details-rally-the-troops",
      "name": "Rally the Troops",
      "type": "spell",
      "domains": [
        "order"
      ],
      "cost": "2",
      "rarity": "uncommon",
      "url": "https://riftdecks.com/cards/details-rally-the-troops",
      "decks_including": 68,
      "inclusion_pct": 5.3,
      "avg_copies_when_included": 1.63,
      "copies_pct": {
        "0": 94.7,
        "1": 1.9,
        "2": 3.3,
        "3+": 0.0
      }
    },
    {
      "slug": "details-corina-veraza",
      "name": "Corina Veraza",
      "type": "unit",
      "domains": [
        "order"
      ],
      "cost": "7C",
      "rarity": "epic",
      "url": "https://riftdecks.com/cards/details-corina-veraza",
      "decks_including": 60,
      "inclusion_pct": 4.6,
      "avg_copies_when_included": 1.93,
      "copies_pct": {
        "0": 95.4,
        "1": 1.0,
        "2": 2.9,
        "3+": 0.7
      }
    },
    {
      "slug": "details-veiled-temple",
      "name": "Veiled Temple",
      "type": "battlefield",
      "domains": [
        "colorless"
      ],
      "cost": "-",
      "rarity": "uncommon",
      "url": "https://riftdecks.com/cards/details-veiled-temple",
      "decks_including": 59,
      "inclusion_pct": 4.6,
      "avg_copies_when_included": 1.0,
      "copies_pct": {
        "0": 95.4,
        "1": 4.6,
        "2": 0.0,
        "3+": 0.0
      }
    },
    {
      "slug": "details-feral-strength",
      "name": "Feral Strength",
      "type": "spell",
      "domains": [
        "calm"
      ],
      "cost": "2",
      "rarity": "common",
      "url": "https://riftdecks.com/cards/details-feral-strength",
      "decks_including": 57,
      "inclusion_pct": 4.4,
      "avg_copies_when_included": 2.04,
      "copies_pct": {
        "0": 95.6,
        "1": 1.7,
        "2": 0.9,
        "3+": 1.9
      }
    },
    {
      "slug": "details-en-garde",
      "name": "En Garde",
      "type": "spell",
      "domains": [
        "calm"
      ],
      "cost": "1",
      "rarity": "common",
      "url": "https://riftdecks.com/cards/details-en-garde",
      "decks_including": 53,
      "inclusion_pct": 4.1,
      "avg_copies_when_included": 2.58,
      "copies_pct": {
        "0": 95.9,
        "1": 0.2,
        "2": 1.2,
        "3+": 2.6
      }
    },
    {
      "slug": "details-heart-of-dark-ice",
      "name": "Heart of Dark Ice",
      "type": "gear",
      "domains": [
        "calm"
      ],
      "cost": "3C",
      "rarity": "rare",
      "url": "https://riftdecks.com/cards/details-heart-of-dark-ice",
      "decks_including": 50,
      "inclusion_pct": 3.9,
      "avg_copies_when_included": 1.22,
      "copies_pct": {
        "0": 96.1,
        "1": 3.0,
        "2": 0.9,
        "3+": 0.0
      }
    },
    {
      "slug": "details-ravenbloom-conservatory",
      "name": "Ravenbloom Conservatory",
      "type": "battlefield",
      "domains": [
        "colorless"
      ],
      "cost": "-",
      "rarity": "uncommon",
      "url": "https://riftdecks.com/cards/details-ravenbloom-conservatory",
      "decks_including": 48,
      "inclusion_pct": 3.7,
      "avg_copies_when_included": 1.0,
      "copies_pct": {
        "0": 96.3,
        "1": 3.7,
        "2": 0.0,
        "3+": 0.0
      }
    },
    {
      "slug": "details-blood-money",
      "name": "Blood Money",
      "type": "spell",
      "domains": [
        "order"
      ],
      "cost": "2",
      "rarity": "uncommon",
      "url": "https://riftdecks.com/cards/details-blood-money",
      "decks_including": 47,
      "inclusion_pct": 3.6,
      "avg_copies_when_included": 2.0,
      "copies_pct": {
        "0": 96.4,
        "1": 0.0,
        "2": 3.6,
        "3+": 0.0
      }
    },
    {
      "slug": "details-the-candlelit-sanctum",
      "name": "The Candlelit Sanctum",
      "type": "battlefield",
      "domains": [
        "colorless"
      ],
      "cost": "-",
      "rarity": "uncommon",
      "url": "https://riftdecks.com/cards/details-the-candlelit-sanctum",
      "decks_including": 47,
      "inclusion_pct": 3.6,
      "avg_copies_when_included": 1.0,
      "copies_pct": {
        "0": 96.4,
        "1": 3.6,
        "2": 0.0,
        "3+": 0.0
      }
    },
    {
      "slug": "details-scuttle-crab",
      "name": "Scuttle Crab",
      "type": "unit",
      "domains": [
        "calm"
      ],
      "cost": "2",
      "rarity": "rare",
      "url": "https://riftdecks.com/cards/details-scuttle-crab",
      "decks_including": 46,
      "inclusion_pct": 3.6,
      "avg_copies_when_included": 1.67,
      "copies_pct": {
        "0": 96.4,
        "1": 1.2,
        "2": 2.4,
        "3+": 0.0
      }
    },
    {
      "slug": "details-seat-of-power",
      "name": "Seat of Power",
      "type": "battlefield",
      "domains": [
        "colorless"
      ],
      "cost": "-",
      "rarity": "uncommon",
      "url": "https://riftdecks.com/cards/details-seat-of-power",
      "decks_including": 42,
      "inclusion_pct": 3.3,
      "avg_copies_when_included": 1.0,
      "copies_pct": {
        "0": 96.7,
        "1": 3.3,
        "2": 0.0,
        "3+": 0.0
      }
    },
    {
      "slug": "details-disarming-rake",
      "name": "Disarming Rake",
      "type": "unit",
      "domains": [
        "calm"
      ],
      "cost": "3C",
      "rarity": "common",
      "url": "https://riftdecks.com/cards/details-disarming-rake",
      "decks_including": 41,
      "inclusion_pct": 3.2,
      "avg_copies_when_included": 1.56,
      "copies_pct": {
        "0": 96.8,
        "1": 1.4,
        "2": 1.8,
        "3+": 0.0
      }
    },
    {
      "slug": "details-steraks-gage",
      "name": "Sterak's Gage",
      "type": "gear",
      "domains": [
        "calm"
      ],
      "cost": "3CC",
      "rarity": "rare",
      "url": "https://riftdecks.com/cards/details-steraks-gage",
      "decks_including": 38,
      "inclusion_pct": 2.9,
      "avg_copies_when_included": 1.53,
      "copies_pct": {
        "0": 97.1,
        "1": 2.1,
        "2": 0.2,
        "3+": 0.7
      }
    },
    {
      "slug": "details-fiora-victorious",
      "name": "Fiora, Victorious",
      "type": "unit",
      "domains": [
        "order"
      ],
      "cost": "4",
      "rarity": "rare",
      "url": "https://riftdecks.com/cards/details-fiora-victorious",
      "decks_including": 38,
      "inclusion_pct": 2.9,
      "avg_copies_when_included": 1.58,
      "copies_pct": {
        "0": 97.1,
        "1": 1.2,
        "2": 1.7,
        "3+": 0.0
      }
    },
    {
      "slug": "details-the-dreaming-tree",
      "name": "The Dreaming Tree",
      "type": "battlefield",
      "domains": [
        "colorless"
      ],
      "cost": "-",
      "rarity": "uncommon",
      "url": "https://riftdecks.com/cards/details-the-dreaming-tree",
      "decks_including": 38,
      "inclusion_pct": 2.9,
      "avg_copies_when_included": 1.0,
      "copies_pct": {
        "0": 97.1,
        "1": 2.9,
        "2": 0.0,
        "3+": 0.0
      }
    },
    {
      "slug": "details-glasc-mixologist",
      "name": "Glasc Mixologist",
      "type": "unit",
      "domains": [
        "order"
      ],
      "cost": "5C",
      "rarity": "uncommon",
      "url": "https://riftdecks.com/cards/details-glasc-mixologist",
      "decks_including": 34,
      "inclusion_pct": 2.6,
      "avg_copies_when_included": 2.0,
      "copies_pct": {
        "0": 97.4,
        "1": 0.0,
        "2": 2.6,
        "3+": 0.0
      }
    },
    {
      "slug": "details-viktor-leader",
      "name": "Viktor, Leader",
      "type": "unit",
      "domains": [
        "order"
      ],
      "cost": "4C",
      "rarity": "showcase",
      "url": "https://riftdecks.com/cards/details-viktor-leader",
      "decks_including": 32,
      "inclusion_pct": 2.5,
      "avg_copies_when_included": 1.38,
      "copies_pct": {
        "0": 97.5,
        "1": 1.5,
        "2": 0.9,
        "3+": 0.0
      }
    },
    {
      "slug": "details-sunken-temple",
      "name": "Sunken Temple",
      "type": "battlefield",
      "domains": [
        "colorless"
      ],
      "cost": "-",
      "rarity": "uncommon",
      "url": "https://riftdecks.com/cards/details-sunken-temple",
      "decks_including": 30,
      "inclusion_pct": 2.3,
      "avg_copies_when_included": 1.0,
      "copies_pct": {
        "0": 97.7,
        "1": 2.3,
        "2": 0.0,
        "3+": 0.0
      }
    },
    {
      "slug": "details-faithful-manufactor",
      "name": "Faithful Manufactor",
      "type": "unit",
      "domains": [
        "order"
      ],
      "cost": "3",
      "rarity": "common",
      "url": "https://riftdecks.com/cards/details-faithful-manufactor",
      "decks_including": 30,
      "inclusion_pct": 2.3,
      "avg_copies_when_included": 2.0,
      "copies_pct": {
        "0": 97.7,
        "1": 0.7,
        "2": 0.9,
        "3+": 0.7
      }
    },
    {
      "slug": "details-seal-of-focus",
      "name": "Seal of Focus",
      "type": "gear",
      "domains": [
        "calm"
      ],
      "cost": "0C",
      "rarity": "epic",
      "url": "https://riftdecks.com/cards/details-seal-of-focus",
      "decks_including": 29,
      "inclusion_pct": 2.2,
      "avg_copies_when_included": 2.0,
      "copies_pct": {
        "0": 97.8,
        "1": 0.0,
        "2": 2.2,
        "3+": 0.0
      }
    },
    {
      "slug": "details-legion-quartermaster",
      "name": "Legion Quartermaster",
      "type": "unit",
      "domains": [
        "calm"
      ],
      "cost": "3",
      "rarity": "uncommon",
      "url": "https://riftdecks.com/cards/details-legion-quartermaster",
      "decks_including": 28,
      "inclusion_pct": 2.2,
      "avg_copies_when_included": 2.5,
      "copies_pct": {
        "0": 97.8,
        "1": 0.0,
        "2": 1.1,
        "3+": 1.1
      }
    },
    {
      "slug": "details-forgotten-monument",
      "name": "Forgotten Monument",
      "type": "battlefield",
      "domains": [
        "colorless"
      ],
      "cost": "-",
      "rarity": "uncommon",
      "url": "https://riftdecks.com/cards/details-forgotten-monument",
      "decks_including": 26,
      "inclusion_pct": 2.0,
      "avg_copies_when_included": 1.0,
      "copies_pct": {
        "0": 98.0,
        "1": 2.0,
        "2": 0.0,
        "3+": 0.0
      }
    },
    {
      "slug": "details-zaun-warrens",
      "name": "Zaun Warrens",
      "type": "battlefield",
      "domains": [
        "colorless"
      ],
      "cost": "-",
      "rarity": "uncommon",
      "url": "https://riftdecks.com/cards/details-zaun-warrens",
      "decks_including": 26,
      "inclusion_pct": 2.0,
      "avg_copies_when_included": 1.0,
      "copies_pct": {
        "0": 98.0,
        "1": 2.0,
        "2": 0.0,
        "3+": 0.0
      }
    },
    {
      "slug": "details-blitzcrank-impassive",
      "name": "Blitzcrank, Impassive",
      "type": "unit",
      "domains": [
        "calm"
      ],
      "cost": "5C",
      "rarity": "rare",
      "url": "https://riftdecks.com/cards/details-blitzcrank-impassive",
      "decks_including": 24,
      "inclusion_pct": 1.9,
      "avg_copies_when_included": 1.62,
      "copies_pct": {
        "0": 98.1,
        "1": 0.7,
        "2": 1.2,
        "3+": 0.0
      }
    },
    {
      "slug": "details-stellacorn-herder",
      "name": "Stellacorn Herder",
      "type": "unit",
      "domains": [
        "calm"
      ],
      "cost": "4",
      "rarity": "uncommon",
      "url": "https://riftdecks.com/cards/details-stellacorn-herder",
      "decks_including": 23,
      "inclusion_pct": 1.8,
      "avg_copies_when_included": 2.39,
      "copies_pct": {
        "0": 98.2,
        "1": 0.0,
        "2": 1.1,
        "3+": 0.7
      }
    },
    {
      "slug": "details-hallowed-tomb",
      "name": "Hallowed Tomb",
      "type": "battlefield",
      "domains": [
        "colorless"
      ],
      "cost": "-",
      "rarity": "uncommon",
      "url": "https://riftdecks.com/cards/details-hallowed-tomb",
      "decks_including": 21,
      "inclusion_pct": 1.6,
      "avg_copies_when_included": 1.0,
      "copies_pct": {
        "0": 98.4,
        "1": 1.6,
        "2": 0.0,
        "3+": 0.0
      }
    },
    {
      "slug": "details-fiora-worthy",
      "name": "Fiora, Worthy",
      "type": "unit",
      "domains": [
        "order"
      ],
      "cost": "3",
      "rarity": "showcase",
      "url": "https://riftdecks.com/cards/details-fiora-worthy",
      "decks_including": 21,
      "inclusion_pct": 1.6,
      "avg_copies_when_included": 2.14,
      "copies_pct": {
        "0": 98.4,
        "1": 0.6,
        "2": 0.2,
        "3+": 0.9
      }
    },
    {
      "slug": "details-altar-of-memories",
      "name": "Altar of Memories",
      "type": "gear",
      "domains": [
        "order"
      ],
      "cost": "2",
      "rarity": "rare",
      "url": "https://riftdecks.com/cards/details-altar-of-memories",
      "decks_including": 19,
      "inclusion_pct": 1.5,
      "avg_copies_when_included": 1.0,
      "copies_pct": {
        "0": 98.5,
        "1": 1.5,
        "2": 0.0,
        "3+": 0.0
      }
    },
    {
      "slug": "details-shepherds-heirloom",
      "name": "Shepherd's Heirloom",
      "type": "gear",
      "domains": [
        "order"
      ],
      "cost": "2",
      "rarity": "common",
      "url": "https://riftdecks.com/cards/details-shepherds-heirloom",
      "decks_including": 18,
      "inclusion_pct": 1.4,
      "avg_copies_when_included": 2.39,
      "copies_pct": {
        "0": 98.6,
        "1": 0.1,
        "2": 0.7,
        "3+": 0.6
      }
    },
    {
      "slug": "details-grove-of-the-god-willow",
      "name": "Grove of the God-Willow",
      "type": "battlefield",
      "domains": [
        "colorless"
      ],
      "cost": "-",
      "rarity": "uncommon",
      "url": "https://riftdecks.com/cards/details-grove-of-the-god-willow",
      "decks_including": 17,
      "inclusion_pct": 1.3,
      "avg_copies_when_included": 1.0,
      "copies_pct": {
        "0": 98.7,
        "1": 1.3,
        "2": 0.0,
        "3+": 0.0
      }
    },
    {
      "slug": "details-the-papertree",
      "name": "The Papertree",
      "type": "battlefield",
      "domains": [
        "colorless"
      ],
      "cost": "-",
      "rarity": "uncommon",
      "url": "https://riftdecks.com/cards/details-the-papertree",
      "decks_including": 17,
      "inclusion_pct": 1.3,
      "avg_copies_when_included": 1.0,
      "copies_pct": {
        "0": 98.7,
        "1": 1.3,
        "2": 0.0,
        "3+": 0.0
      }
    },
    {
      "slug": "details-vengeance",
      "name": "Vengeance",
      "type": "spell",
      "domains": [
        "order"
      ],
      "cost": "4CC",
      "rarity": "uncommon",
      "url": "https://riftdecks.com/cards/details-vengeance",
      "decks_including": 16,
      "inclusion_pct": 1.2,
      "avg_copies_when_included": 2.88,
      "copies_pct": {
        "0": 98.8,
        "1": 0.1,
        "2": 0.0,
        "3+": 1.2
      }
    },
    {
      "slug": "details-aphelios-exalted",
      "name": "Aphelios, Exalted",
      "type": "unit",
      "domains": [
        "calm"
      ],
      "cost": "4C",
      "rarity": "showcase",
      "url": "https://riftdecks.com/cards/details-aphelios-exalted",
      "decks_including": 16,
      "inclusion_pct": 1.2,
      "avg_copies_when_included": 1.38,
      "copies_pct": {
        "0": 98.8,
        "1": 0.8,
        "2": 0.5,
        "3+": 0.0
      }
    },
    {
      "slug": "details-drag-under",
      "name": "Drag Under",
      "type": "spell",
      "domains": [
        "order"
      ],
      "cost": "5C",
      "rarity": "uncommon",
      "url": "https://riftdecks.com/cards/details-drag-under",
      "decks_including": 15,
      "inclusion_pct": 1.2,
      "avg_copies_when_included": 3.0,
      "copies_pct": {
        "0": 98.8,
        "1": 0.0,
        "2": 0.0,
        "3+": 1.2
      }
    },
    {
      "slug": "details-spirits-refuge",
      "name": "Spirit's Refuge",
      "type": "gear",
      "domains": [
        "calm"
      ],
      "cost": "2C",
      "rarity": "uncommon",
      "url": "https://riftdecks.com/cards/details-spirits-refuge",
      "decks_including": 15,
      "inclusion_pct": 1.2,
      "avg_copies_when_included": 1.0,
      "copies_pct": {
        "0": 98.8,
        "1": 1.2,
        "2": 0.0,
        "3+": 0.0
      }
    },
    {
      "slug": "details-vanguard-armory",
      "name": "Vanguard Armory",
      "type": "gear",
      "domains": [
        "order"
      ],
      "cost": "7C",
      "rarity": "uncommon",
      "url": "https://riftdecks.com/cards/details-vanguard-armory",
      "decks_including": 14,
      "inclusion_pct": 1.1,
      "avg_copies_when_included": 1.0,
      "copies_pct": {
        "0": 98.9,
        "1": 1.1,
        "2": 0.0,
        "3+": 0.0
      }
    },
    {
      "slug": "details-mystic-reversal",
      "name": "Mystic Reversal",
      "type": "spell",
      "domains": [
        "calm"
      ],
      "cost": "4CCC",
      "rarity": "epic",
      "url": "https://riftdecks.com/cards/details-mystic-reversal",
      "decks_including": 13,
      "inclusion_pct": 1.0,
      "avg_copies_when_included": 1.0,
      "copies_pct": {
        "0": 99.0,
        "1": 1.0,
        "2": 0.0,
        "3+": 0.0
      }
    },
    {
      "slug": "details-sigil-of-the-storm",
      "name": "Sigil of the Storm",
      "type": "battlefield",
      "domains": [
        "colorless"
      ],
      "cost": "-",
      "rarity": "uncommon",
      "url": "https://riftdecks.com/cards/details-sigil-of-the-storm",
      "decks_including": 13,
      "inclusion_pct": 1.0,
      "avg_copies_when_included": 1.0,
      "copies_pct": {
        "0": 99.0,
        "1": 1.0,
        "2": 0.0,
        "3+": 0.0
      }
    },
    {
      "slug": "details-block",
      "name": "Block",
      "type": "spell",
      "domains": [
        "calm"
      ],
      "cost": "2",
      "rarity": "uncommon",
      "url": "https://riftdecks.com/cards/details-block",
      "decks_including": 12,
      "inclusion_pct": 0.9,
      "avg_copies_when_included": 1.0,
      "copies_pct": {
        "0": 99.1,
        "1": 0.9,
        "2": 0.0,
        "3+": 0.0
      }
    },
    {
      "slug": "details-zhonyas-hourglass",
      "name": "Zhonya's Hourglass",
      "type": "gear",
      "domains": [
        "calm"
      ],
      "cost": "2",
      "rarity": "rare",
      "url": "https://riftdecks.com/cards/details-zhonyas-hourglass",
      "decks_including": 12,
      "inclusion_pct": 0.9,
      "avg_copies_when_included": 3.0,
      "copies_pct": {
        "0": 99.1,
        "1": 0.0,
        "2": 0.0,
        "3+": 0.9
      }
    },
    {
      "slug": "details-the-grand-plaza",
      "name": "The Grand Plaza",
      "type": "battlefield",
      "domains": [
        "colorless"
      ],
      "cost": "-",
      "rarity": "uncommon",
      "url": "https://riftdecks.com/cards/details-the-grand-plaza",
      "decks_including": 11,
      "inclusion_pct": 0.9,
      "avg_copies_when_included": 1.0,
      "copies_pct": {
        "0": 99.1,
        "1": 0.9,
        "2": 0.0,
        "3+": 0.0
      }
    },
    {
      "slug": "details-baited-hook",
      "name": "Baited Hook",
      "type": "gear",
      "domains": [
        "order"
      ],
      "cost": "3",
      "rarity": "epic",
      "url": "https://riftdecks.com/cards/details-baited-hook",
      "decks_including": 11,
      "inclusion_pct": 0.9,
      "avg_copies_when_included": 3.0,
      "copies_pct": {
        "0": 99.1,
        "1": 0.0,
        "2": 0.0,
        "3+": 0.9
      }
    },
    {
      "slug": "details-the-arenas-greatest",
      "name": "The Arena's Greatest",
      "type": "battlefield",
      "domains": [
        "colorless"
      ],
      "cost": "-",
      "rarity": "uncommon",
      "url": "https://riftdecks.com/cards/details-the-arenas-greatest",
      "decks_including": 11,
      "inclusion_pct": 0.9,
      "avg_copies_when_included": 1.0,
      "copies_pct": {
        "0": 99.1,
        "1": 0.9,
        "2": 0.0,
        "3+": 0.0
      }
    },
    {
      "slug": "details-machine-evangel",
      "name": "Machine Evangel",
      "type": "unit",
      "domains": [
        "order"
      ],
      "cost": "5C",
      "rarity": "rare",
      "url": "https://riftdecks.com/cards/details-machine-evangel",
      "decks_including": 11,
      "inclusion_pct": 0.9,
      "avg_copies_when_included": 3.0,
      "copies_pct": {
        "0": 99.1,
        "1": 0.0,
        "2": 0.0,
        "3+": 0.9
      }
    },
    {
      "slug": "details-harnessed-dragon",
      "name": "Harnessed Dragon",
      "type": "unit",
      "domains": [
        "order"
      ],
      "cost": "8CC",
      "rarity": "rare",
      "url": "https://riftdecks.com/cards/details-harnessed-dragon",
      "decks_including": 11,
      "inclusion_pct": 0.9,
      "avg_copies_when_included": 2.0,
      "copies_pct": {
        "0": 99.1,
        "1": 0.0,
        "2": 0.9,
        "3+": 0.0
      }
    },
    {
      "slug": "details-soaring-scout",
      "name": "Soaring Scout",
      "type": "unit",
      "domains": [
        "order"
      ],
      "cost": "2",
      "rarity": "common",
      "url": "https://riftdecks.com/cards/details-soaring-scout",
      "decks_including": 11,
      "inclusion_pct": 0.9,
      "avg_copies_when_included": 3.0,
      "copies_pct": {
        "0": 99.1,
        "1": 0.0,
        "2": 0.0,
        "3+": 0.9
      }
    },
    {
      "slug": "details-karthus-eternal",
      "name": "Karthus, Eternal",
      "type": "unit",
      "domains": [
        "order"
      ],
      "cost": "3C",
      "rarity": "rare",
      "url": "https://riftdecks.com/cards/details-karthus-eternal",
      "decks_including": 11,
      "inclusion_pct": 0.9,
      "avg_copies_when_included": 2.0,
      "copies_pct": {
        "0": 99.1,
        "1": 0.0,
        "2": 0.9,
        "3+": 0.0
      }
    },
    {
      "slug": "details-windswept-hillock",
      "name": "Windswept Hillock",
      "type": "battlefield",
      "domains": [
        "colorless"
      ],
      "cost": "-",
      "rarity": "uncommon",
      "url": "https://riftdecks.com/cards/details-windswept-hillock",
      "decks_including": 9,
      "inclusion_pct": 0.7,
      "avg_copies_when_included": 1.0,
      "copies_pct": {
        "0": 99.3,
        "1": 0.7,
        "2": 0.0,
        "3+": 0.0
      }
    },
    {
      "slug": "details-vanguard-captain",
      "name": "Vanguard Captain",
      "type": "unit",
      "domains": [
        "order"
      ],
      "cost": "3C",
      "rarity": "common",
      "url": "https://riftdecks.com/cards/details-vanguard-captain",
      "decks_including": 9,
      "inclusion_pct": 0.7,
      "avg_copies_when_included": 1.0,
      "copies_pct": {
        "0": 99.3,
        "1": 0.7,
        "2": 0.0,
        "3+": 0.0
      }
    },
    {
      "slug": "details-rune-prison",
      "name": "Rune Prison",
      "type": "spell",
      "domains": [
        "calm"
      ],
      "cost": "2C",
      "rarity": "common",
      "url": "https://riftdecks.com/cards/details-rune-prison",
      "decks_including": 9,
      "inclusion_pct": 0.7,
      "avg_copies_when_included": 1.0,
      "copies_pct": {
        "0": 99.3,
        "1": 0.7,
        "2": 0.0,
        "3+": 0.0
      }
    },
    {
      "slug": "details-guardian-of-the-passage",
      "name": "Guardian of the Passage",
      "type": "unit",
      "domains": [
        "calm"
      ],
      "cost": "6",
      "rarity": "common",
      "url": "https://riftdecks.com/cards/details-guardian-of-the-passage",
      "decks_including": 9,
      "inclusion_pct": 0.7,
      "avg_copies_when_included": 3.0,
      "copies_pct": {
        "0": 99.3,
        "1": 0.0,
        "2": 0.0,
        "3+": 0.7
      }
    },
    {
      "slug": "details-trove-golem",
      "name": "Trove Golem",
      "type": "unit",
      "domains": [
        "order"
      ],
      "cost": "8CC",
      "rarity": "rare",
      "url": "https://riftdecks.com/cards/details-trove-golem",
      "decks_including": 9,
      "inclusion_pct": 0.7,
      "avg_copies_when_included": 3.0,
      "copies_pct": {
        "0": 99.3,
        "1": 0.0,
        "2": 0.0,
        "3+": 0.7
      }
    },
    {
      "slug": "details-forgotten-signpost",
      "name": "Forgotten Signpost",
      "type": "gear",
      "domains": [
        "calm"
      ],
      "cost": "2",
      "rarity": "uncommon",
      "url": "https://riftdecks.com/cards/details-forgotten-signpost",
      "decks_including": 8,
      "inclusion_pct": 0.6,
      "avg_copies_when_included": 1.12,
      "copies_pct": {
        "0": 99.4,
        "1": 0.5,
        "2": 0.1,
        "3+": 0.0
      }
    },
    {
      "slug": "details-solari-shieldbearer",
      "name": "Solari Shieldbearer",
      "type": "unit",
      "domains": [
        "calm"
      ],
      "cost": "3",
      "rarity": "common",
      "url": "https://riftdecks.com/cards/details-solari-shieldbearer",
      "decks_including": 8,
      "inclusion_pct": 0.6,
      "avg_copies_when_included": 1.0,
      "copies_pct": {
        "0": 99.4,
        "1": 0.6,
        "2": 0.0,
        "3+": 0.0
      }
    },
    {
      "slug": "details-clockwork-keeper",
      "name": "Clockwork Keeper",
      "type": "unit",
      "domains": [
        "calm"
      ],
      "cost": "2",
      "rarity": "common",
      "url": "https://riftdecks.com/cards/details-clockwork-keeper",
      "decks_including": 7,
      "inclusion_pct": 0.5,
      "avg_copies_when_included": 3.0,
      "copies_pct": {
        "0": 99.5,
        "1": 0.0,
        "2": 0.0,
        "3+": 0.5
      }
    },
    {
      "slug": "details-jax-unmatched",
      "name": "Jax, Unmatched",
      "type": "unit",
      "domains": [
        "calm"
      ],
      "cost": "5C",
      "rarity": "showcase",
      "url": "https://riftdecks.com/cards/details-jax-unmatched",
      "decks_including": 6,
      "inclusion_pct": 0.5,
      "avg_copies_when_included": 3.0,
      "copies_pct": {
        "0": 99.5,
        "1": 0.0,
        "2": 0.0,
        "3+": 0.5
      }
    },
    {
      "slug": "details-flurry-of-feathers",
      "name": "Flurry of Feathers",
      "type": "spell",
      "domains": [
        "calm"
      ],
      "cost": "4CC",
      "rarity": "uncommon",
      "url": "https://riftdecks.com/cards/details-flurry-of-feathers",
      "decks_including": 6,
      "inclusion_pct": 0.5,
      "avg_copies_when_included": 1.67,
      "copies_pct": {
        "0": 99.5,
        "1": 0.2,
        "2": 0.3,
        "3+": 0.0
      }
    },
    {
      "slug": "details-ashe-focused",
      "name": "Ashe, Focused",
      "type": "unit",
      "domains": [
        "order"
      ],
      "cost": "5C",
      "rarity": "rare",
      "url": "https://riftdecks.com/cards/details-ashe-focused",
      "decks_including": 3,
      "inclusion_pct": 0.2,
      "avg_copies_when_included": 1.0,
      "copies_pct": {
        "0": 99.8,
        "1": 0.2,
        "2": 0.0,
        "3+": 0.0
      }
    },
    {
      "slug": "details-forbidding-waste",
      "name": "Forbidding Waste",
      "type": "battlefield",
      "domains": [
        "colorless"
      ],
      "cost": "-",
      "rarity": "uncommon",
      "url": "https://riftdecks.com/cards/details-forbidding-waste",
      "decks_including": 3,
      "inclusion_pct": 0.2,
      "avg_copies_when_included": 1.0,
      "copies_pct": {
        "0": 99.8,
        "1": 0.2,
        "2": 0.0,
        "3+": 0.0
      }
    },
    {
      "slug": "details-forge-of-the-future",
      "name": "Forge of the Future",
      "type": "gear",
      "domains": [
        "order"
      ],
      "cost": "2",
      "rarity": "common",
      "url": "https://riftdecks.com/cards/details-forge-of-the-future",
      "decks_including": 2,
      "inclusion_pct": 0.2,
      "avg_copies_when_included": 1.0,
      "copies_pct": {
        "0": 99.8,
        "1": 0.2,
        "2": 0.0,
        "3+": 0.0
      }
    },
    {
      "slug": "details-gardens-of-becoming",
      "name": "Gardens of Becoming",
      "type": "battlefield",
      "domains": [
        "colorless"
      ],
      "cost": "-",
      "rarity": "uncommon",
      "url": "https://riftdecks.com/cards/details-gardens-of-becoming",
      "decks_including": 2,
      "inclusion_pct": 0.2,
      "avg_copies_when_included": 1.0,
      "copies_pct": {
        "0": 99.8,
        "1": 0.2,
        "2": 0.0,
        "3+": 0.0
      }
    },
    {
      "slug": "details-the-ruination",
      "name": "The Ruination",
      "type": "spell",
      "domains": [
        "order"
      ],
      "cost": "9CCC",
      "rarity": "epic",
      "url": "https://riftdecks.com/cards/details-the-ruination",
      "decks_including": 1,
      "inclusion_pct": 0.1,
      "avg_copies_when_included": 1.0,
      "copies_pct": {
        "0": 99.9,
        "1": 0.1,
        "2": 0.0,
        "3+": 0.0
      }
    },
    {
      "slug": "details-vilemaw",
      "name": "Vilemaw",
      "type": "unit",
      "domains": [
        "calm"
      ],
      "cost": "8CC",
      "rarity": "epic",
      "url": "https://riftdecks.com/cards/details-vilemaw",
      "decks_including": 1,
      "inclusion_pct": 0.1,
      "avg_copies_when_included": 2.0,
      "copies_pct": {
        "0": 99.9,
        "1": 0.0,
        "2": 0.1,
        "3+": 0.0
      }
    }
  ]
}